as1/vikrants uploaded/Assignment 1/ques1/full_adder.v
module full_adder(A,B,Cin,Sum,Cout);
input A,B,Cin;
output Sum,Cout; //A,B ->1 bit input numbers Cin->Carry input Cout->Carry Output Sum->Sum
wire t1,t2,t3;   //Temporary wires for storing temporary values
xor(Sum,A,B,Cin);  //Getting Sum
and(t1,A,B);
and(t2,B,Cin);
and(t3,A,Cin);
or (Cout,t1,t2,t3); //Getting Carry out->Cout
endmodule

as1/vikrants uploaded/Assignment 1/ques1/full_adder_test.v
`include "full_adder.v"
module full_adder_test;
reg A,B,Cin;
wire Sum,Cout;
full_adder f(.A(A),.B(B),.Cin(Cin),.Sum(Sum),.Cout(Cout));
initial begin
    $dumpfile("full_adder.vcd");
    $dumpvars(0,full_adder_test);
    $monitor($time, " A=%b,B=%b,Cin=%b,Sum=%b,Cout=%b",A,B,Cin,Sum,Cout);
    #1 A=0;B=0;Cin=0;
    #1 A=0;B=0;Cin=1;
    #1 A=0;B=1;Cin=0;
    #1 A=0;B=1;Cin=1;
    #1 A=1;B=0;Cin=0;
    #1 A=1;B=0;Cin=1;
    #1 A=1;B=1;Cin=0;
    #1 A=1;B=1;Cin=1;
    end
endmodule

as1/vikrants uploaded/Assignment 1/ques1/full_adder.vcd
$date
	Tue Aug 15 18:23:05 2023
$end
$version
	Icarus Verilog
$end
$timescale
	1s
$end
$scope module full_adder_test $end
$var wire 1 ! Sum $end
$var wire 1 " Cout $end
$var reg 1 # A $end
$var reg 1 $ B $end
$var reg 1 % Cin $end
$scope module f $end
$var wire 1 # A $end
$var wire 1 $ B $end
$var wire 1 % Cin $end
$var wire 1 " Cout $end
$var wire 1 ! Sum $end
$var wire 1 & t1 $end
$var wire 1 ' t2 $end
$var wire 1 ( t3 $end
$upscope $end
$upscope $end
$enddefinitions $end
#0
$dumpvars
x(
x'
x&
x%
x$
x#
x"
x!
$end
#1
0"
0'
0!
0&
0(
0%
0$
0#
#2
1!
1%
#3
0%
1$
#4
1"
0!
1'
1%
#5
0"
0'
1!
0%
0$
1#
#6
1"
0!
1(
1%
#7
0(
1&
0%
1$
#8
1!
1'
1(
1%
