as1/vikrants uploaded/Assignment 1/ques3/d_flipflop.v
module d_flipflop(d,clk,rst,q);
input d,clk,rst;                  // d->input clk->clock rst->reset q->output
output reg q;

always @(posedge clk) begin
    if (rst) begin               // when rst is 1 then output is set to 0
         q=1'b0;    
    end
    else begin
    q=d;                        // else output is d

    end
end
endmodule

as1/vikrants uploaded/Assignment 1/ques3/d_ff_test.v
`include "d_flipflop.v"
module dff_test;
wire q;
reg clk,rst,d;

d_flipflop D(d,clk,rst,q);           // d->input clk->clock rst->reset q->output
initial
        clk = 0;
    always
      #5 clk = ~clk;
initial
       d = 0;
    always
      #3 d = ~d;

initial begin
    $dumpfile("d_ff_test.vcd");      
    $dumpvars(0,dff_test);
    #0 rst=1;                        // At t=0 reset is set to 1
    #1 rst=0;                        // At t=1 reset is set to 0
    $monitor("time=%t,clk=%b,d=%b,q=%b",$time,clk,d,q);
   
#40 $finish;
end
endmodule

as1/vikrants uploaded/Assignment 1/ques3/d_ff_test.vcd
$date
	Tue Aug 15 19:04:30 2023
$end
$version
	Icarus Verilog
$end
$timescale
	1s
$end
$scope module dff_test $end
$var wire 1 ! q $end
$var reg 1 " clk $end
$var reg 1 # d $end
$var reg 1 $ rst $end
$scope module D $end
$var wire 1 " clk $end
$var wire 1 # d $end
$var wire 1 $ rst $end
$var reg 1 ! q $end
$upscope $end
$upscope $end
$enddefinitions $end
#0
$dumpvars
1$
0#
0"
x!
$end
#1
0$
#3
1#
#5
1!
1"
#6
0#
#9
1#
#10
0"
#12
0#
#15
1#
1"
#18
0#
#20
0"
#21
1#
#24
0#
#25
0!
1"
#27
1#
#30
0#
0"
#33
1#
#35
1!
1"
#36
0#
#39
1#
