as1/vikrants uploaded/Assignment 1/ques3/d_flipflop.v
module d_flipflop(d,clk,rst,q);
input d,clk,rst;                  // d->input clk->clock rst->reset q->output
output reg q;

always @(posedge clk) begin
    if (rst) begin               // when rst is 1 then output is set to 0
         q=1'b0;    
    end
    else begin
    q=d;                        // else output is d

    end
end
endmodule

as1/vikrants uploaded/Assignment 1/ques3/john_count.v
`include "d_flipflop.v"
module johnson(clk,rst,state);
input clk,rst;
output [0:3]state;  //clk-> clock rst->reset state->values of q at the various flipflops
d_flipflop d1(.d(~state[3]),.clk(clk),.rst(rst),.q(state[0]));
d_flipflop d2(.d(state[0]),.clk(clk),.rst(rst),.q(state[1]));
d_flipflop d3(.d(state[1]),.clk(clk),.rst(rst),.q(state[2]));
d_flipflop d4(.d(state[2]),.clk(clk),.rst(rst),.q(state[3]));
endmodule

as1/vikrants uploaded/Assignment 1/ques3/john_test.v
`include "john_count.v"
module johncount_test;
reg clk,rst;
wire [0:3]state;   //clk-> clock rst->reset state->values of q at the various flipflops
johnson j(.clk(clk),.rst(rst),.state(state));

initial
        clk = 0;
    always
      #5 clk = ~clk;

initial 
begin
    #0 rst=1;
    #10 rst=0;
    #100 rst=1;  //Reseting the johnson counter so that it starts from its initial state
    #105 rst=0;
    #200 $finish;
end
initial 
begin
    $dumpfile("john_test.vcd");
    $dumpvars(0,johncount_test);
    $monitor("time=%t,reset=%b,clock=%b,state=%b",$time,rst,clk,state);
end
endmodule

as1/vikrants uploaded/Assignment 1/ques3/john_test.vcd
$date
	Sat Aug 26 18:58:49 2023
$end
$version
	Icarus Verilog
$end
$timescale
	1s
$end
$scope module johncount_test $end
$var wire 4 ! state [0:3] $end
$var reg 1 " clk $end
$var reg 1 # rst $end
$scope module j $end
$var wire 1 " clk $end
$var wire 1 # rst $end
$var wire 4 $ state [0:3] $end
$scope module d1 $end
$var wire 1 " clk $end
$var wire 1 % d $end
$var wire 1 # rst $end
$var reg 1 & q $end
$upscope $end
$scope module d2 $end
$var wire 1 " clk $end
$var wire 1 ' d $end
$var wire 1 # rst $end
$var reg 1 ( q $end
$upscope $end
$scope module d3 $end
$var wire 1 " clk $end
$var wire 1 ) d $end
$var wire 1 # rst $end
$var reg 1 * q $end
$upscope $end
$scope module d4 $end
$var wire 1 " clk $end
$var wire 1 + d $end
$var wire 1 # rst $end
$var reg 1 , q $end
$upscope $end
$upscope $end
$upscope $end
$enddefinitions $end
#0
$dumpvars
x,
x+
x*
x)
x(
x'
x&
x%
bx $
1#
0"
bx !
$end
#5
1%
0'
0)
0+
0&
0(
0*
b0 !
b0 $
0,
1"
#10
0"
0#
#15
1'
b1000 !
b1000 $
1&
1"
#20
0"
#25
1)
b1100 !
b1100 $
1(
1"
#30
0"
#35
1+
b1110 !
b1110 $
1*
1"
#40
0"
#45
0%
b1111 !
b1111 $
1,
1"
#50
0"
#55
0'
b111 !
b111 $
0&
1"
#60
0"
#65
0)
b11 !
b11 $
0(
1"
#70
0"
#75
0+
b1 !
b1 $
0*
1"
#80
0"
#85
1%
b0 !
b0 $
0,
1"
#90
0"
#95
1'
b1000 !
b1000 $
1&
1"
#100
0"
#105
1)
b1100 !
b1100 $
1(
1"
#110
0"
1#
#115
0)
0'
0(
b0 !
b0 $
0&
1"
#120
0"
#125
1"
#130
0"
#135
1"
#140
0"
#145
1"
#150
0"
#155
1"
#160
0"
#165
1"
#170
0"
#175
1"
#180
0"
#185
1"
#190
0"
#195
1"
#200
0"
#205
1"
#210
0"
#215
1'
b1000 !
b1000 $
1&
1"
0#
#220
0"
#225
1)
b1100 !
b1100 $
1(
1"
#230
0"
#235
1+
b1110 !
b1110 $
1*
1"
#240
0"
#245
0%
b1111 !
b1111 $
1,
1"
#250
0"
#255
0'
b111 !
b111 $
0&
1"
#260
0"
#265
0)
b11 !
b11 $
0(
1"
#270
0"
#275
0+
b1 !
b1 $
0*
1"
#280
0"
#285
1%
b0 !
b0 $
0,
1"
#290
0"
#295
1'
b1000 !
b1000 $
1&
1"
#300
0"
#305
1)
b1100 !
b1100 $
1(
1"
#310
0"
#315
1+
b1110 !
b1110 $
1*
1"
#320
0"
#325
0%
b1111 !
b1111 $
1,
1"
#330
0"
#335
0'
b111 !
b111 $
0&
1"
#340
0"
#345
0)
b11 !
b11 $
0(
1"
#350
0"
#355
0+
b1 !
b1 $
0*
1"
#360
0"
#365
1%
b0 !
b0 $
0,
1"
#370
0"
#375
1'
b1000 !
b1000 $
1&
1"
#380
0"
#385
1)
b1100 !
b1100 $
1(
1"
#390
0"
#395
1+
b1110 !
b1110 $
1*
1"
#400
0"
#405
0%
b1111 !
b1111 $
1,
1"
#410
0"
#415
0'
b111 !
b111 $
0&
1"
